workstack/__init__.py
workstack/__main__.py
workstack/version.py
workstack/cli/__init__.py
workstack/cli/activation.py
workstack/cli/cli.py
workstack/cli/config.py
workstack/cli/core.py
workstack/cli/debug.py
workstack/cli/graphite.py
workstack/cli/output.py
workstack/cli/shell_utils.py
workstack/cli/subprocess_utils.py
workstack/cli/tree.py
workstack/cli/commands/__init__.py
workstack/cli/commands/completion.py
workstack/cli/commands/config.py
workstack/cli/commands/consolidate.py
workstack/cli/commands/create.py
workstack/cli/commands/current.py
workstack/cli/commands/down.py
workstack/cli/commands/gt.py
workstack/cli/commands/init.py
workstack/cli/commands/jump.py
workstack/cli/commands/list.py
workstack/cli/commands/move.py
workstack/cli/commands/prepare_cwd_recovery.py
workstack/cli/commands/remove.py
workstack/cli/commands/rename.py
workstack/cli/commands/shell_integration.py
workstack/cli/commands/status.py
workstack/cli/commands/switch.py
workstack/cli/commands/sync.py
workstack/cli/commands/tree.py
workstack/cli/commands/up.py
workstack/cli/commands/land_stack/README.md
workstack/cli/commands/land_stack/__init__.py
workstack/cli/commands/land_stack/cleanup.py
workstack/cli/commands/land_stack/command.py
workstack/cli/commands/land_stack/discovery.py
workstack/cli/commands/land_stack/display.py
workstack/cli/commands/land_stack/execution.py
workstack/cli/commands/land_stack/models.py
workstack/cli/commands/land_stack/output.py
workstack/cli/commands/land_stack/validation.py
workstack/cli/presets/dagster.toml
workstack/cli/presets/generic.toml
workstack/cli/shell_integration/bash_wrapper.sh
workstack/cli/shell_integration/fish_wrapper.fish
workstack/cli/shell_integration/handler.py
workstack/cli/shell_integration/zsh_wrapper.sh
workstack/core/__init__.py
workstack/core/branch_metadata.py
workstack/core/completion_ops.py
workstack/core/consolidation_utils.py
workstack/core/context.py
workstack/core/display_utils.py
workstack/core/file_utils.py
workstack-0.1.26.dist-info/METADATA
workstack-0.1.26.dist-info/WHEEL
workstack-0.1.26.dist-info/entry_points.txt
workstack-0.1.26.dist-info/RECORD
