Metadata-Version: 2.4
Name: workstack
Version: 0.1.26
Summary: Add your description here
Author-email: Dagster Labs <hello@dagsterlabs.com>
Requires-Python: >=3.13
Requires-Dist: click>=8.1.7
Requires-Dist: python-frontmatter>=1.0.0
Requires-Dist: tomlkit>=0.12.0
